fhempy/__init__.py
fhempy/lib/__init__.py
fhempy/lib/aktionsfinder/README.md
fhempy/lib/aktionsfinder/__init__.py
fhempy/lib/aktionsfinder/aktionsfinder.py
fhempy/lib/aktionsfinder/manifest.json
fhempy/lib/alphaess/README.md
fhempy/lib/alphaess/__init__.py
fhempy/lib/alphaess/alphaesscloud.py
fhempy/lib/alphaess/manifest.json
fhempy/lib/arp_presence/README.md
fhempy/lib/arp_presence/__init__.py
fhempy/lib/arp_presence/arp_presence.py
fhempy/lib/arp_presence/manifest.json
fhempy/lib/ble_monitor/README.md
fhempy/lib/ble_monitor/__init__.py
fhempy/lib/ble_monitor/ble_monitor.py
fhempy/lib/ble_monitor/blemonitor.py
fhempy/lib/ble_monitor/bt_helpers.py
fhempy/lib/ble_monitor/const.py
fhempy/lib/ble_monitor/hcidump.py
fhempy/lib/ble_monitor/helper.py
fhempy/lib/ble_monitor/manifest.json
fhempy/lib/ble_presence/README.md
fhempy/lib/ble_presence/__init__.py
fhempy/lib/ble_presence/ble_presence.py
fhempy/lib/ble_presence/manifest.json
fhempy/lib/ble_reset/README.md
fhempy/lib/ble_reset/__init__.py
fhempy/lib/ble_reset/ble_reset.py
fhempy/lib/ble_reset/manifest.json
fhempy/lib/blue_connect/README.md
fhempy/lib/blue_connect/__init__.py
fhempy/lib/blue_connect/blue_connect.py
fhempy/lib/blue_connect/manifest.json
fhempy/lib/bt_presence/README.md
fhempy/lib/bt_presence/__init__.py
fhempy/lib/bt_presence/bt_presence.py
fhempy/lib/bt_presence/manifest.json
fhempy/lib/core/__init__.py
fhempy/lib/core/bluetoothctl.py
fhempy/lib/core/bluetoothle.py
fhempy/lib/core/discover_fhempy/__init__.py
fhempy/lib/core/discover_fhempy/discover_fhempy.py
fhempy/lib/core/discover_fhempy/manifest.json
fhempy/lib/core/manifest.json
fhempy/lib/core/ssdp.py
fhempy/lib/core/zeroconf.py
fhempy/lib/ddnssde/README.md
fhempy/lib/ddnssde/__init__.py
fhempy/lib/ddnssde/ddnssde.py
fhempy/lib/ddnssde/manifest.json
fhempy/lib/discover_ble/__init__.py
fhempy/lib/discover_ble/discover_ble.py
fhempy/lib/discover_ble/manifest.json
fhempy/lib/discover_mdns/__init__.py
fhempy/lib/discover_mdns/discover_mdns.py
fhempy-0.1.753.dist-info/LICENSE
fhempy-0.1.753.dist-info/METADATA
fhempy-0.1.753.dist-info/WHEEL
fhempy-0.1.753.dist-info/entry_points.txt
fhempy-0.1.753.dist-info/RECORD
