Metadata-Version: 2.3
Name: fhempy
Version: 0.1.753
Summary: Python binding for FHEM to support Python modules
Author: Dominik Karall
Author-email: dominik.karall@gmail.com
Requires-Python: >=3.9,<4.0
Classifier: Programming Language :: Python :: 3
Classifier: Programming Language :: Python :: 3.9
Classifier: Programming Language :: Python :: 3.10
Classifier: Programming Language :: Python :: 3.11
Classifier: Programming Language :: Python :: 3.12
Classifier: Programming Language :: Python :: 3.13
Requires-Dist: aiofiles (==23.2.1)
Requires-Dist: aiohttp[speedups] (==3.9.5)
Requires-Dist: async-upnp-client (==0.38.3)
Requires-Dist: ifaddr (==0.2.0)
Requires-Dist: importlib_metadata (==7.1.0)
Requires-Dist: markdown2 (==2.4.13)
Requires-Dist: packaging (==24.0)
Requires-Dist: pexpect (==4.9.0)
Requires-Dist: pycryptodomex (==3.20.0)
Requires-Dist: requests (==2.32.2)
Requires-Dist: websockets (==12.0)
Requires-Dist: zeroconf (==0.132.2)
Project-URL: Bug Tracker, https://github.com/fhempy/fhempy/issues
Project-URL: Homepage, https://github.com/fhempy/fhempy
Project-URL: Sponsorship, https://github.com/sponsors/fhempy
